{

    "7": [
        {
            "value": 5,
            "isAnswered": false,
            "question": "مين سبح من المشرفين"
        },
        {
            "value": 10,
            "isAnswered": false,
            "question": "كيف نحافظ على أمانة الصلاة؟"
        },
        {
            "value": 20,
            "isAnswered": false,
            "question": "اذكر واحدة من الطرق التي يمكن أن تزيد بها محبتك للرسول ﷺ"
        },
        {
            "value": 40,
            "isAnswered": false,
            "question": "أكمل الكلمات الناقصة  _____ خيرٌ من ____"
        },
        {
            "value": 50,
            "isAnswered": false,
            "question": "بما يتعلق بالوقت أكمل ، يابن ادم انما انت _____ _______"
        }
    ],
    "      6": [
        {
            "value": 5,
            "isAnswered": false,
            "question": "اعطني مثال على شيء هام وعاجل"
        },
        {
            "value": 10,
            "isAnswered": false,
            "question": "كيف يمكننا تحقيق أمانة الوقت؟"
        },
        {
            "value": 20,
            "isAnswered": false,
            "question": "اذكر أحد المواقف التي يظهر فيها حب الصحابة للرسول ﷺ"
        },
        {
            "value": 40,
            "isAnswered": false,
            "question": "ما هي العلامة الكبرى لمحبة الرسول ﷺ؟"
        },
        {
            "value": 50,
            "isAnswered": false,
            "question": "اذكر أحد الأسباب التي تجعل إدارة الوقت أمرًا مهمًا."
        }
    ],
    "     5": [
        {
            "value": 5,
            "isAnswered": false,
            "question": "اذكر أهمية الرياضة والتغذية في حياة الإنسان."
        },
        {
            "value": 10,
            "isAnswered": false,
            "question": "اذكر أحد لصوص الأمانة"

        },
        {
            "value": 20,
            "isAnswered": false,
            "question": "ما هي قاعدة 8-8-8 وكيف يمكن تطبيقها؟"
        },
        {
            "value": 40,
            "isAnswered": false,
            "question": "لماذا تعتبر قصة الآن يا عمر مثالًا على محبة الرسول ﷺ؟"
        },
        {
            "value": 50,
            "isAnswered": false,
            "question": "  : لدينا 10 شجريات، نود زراعتها في 5 خطوط مستقيمة، بحيث يكون في كل خط 4 شجيرات، فكيف يمكن توزيعها ؟ "
        }
    ],
    "    4": [
        { "value": 5, "isAnswered": false, "question": " ما هي أركان التوازن في الحياة   " },
        {
            "value": 10,
            "isAnswered": false,
            "question": "  ما معنى الأمانة كما ورد في اللقاء؟   "
        },
        {
            "value": 20,
            "isAnswered": false,
            "question": "    : ما معنى المثابرة، ولماذا تعتبر مفتاح النجاح؟  "
        },
        {
            "value": 40,
            "isAnswered": false,
            "question": " اذكر مثالًا معاصرًا يعبر عن قيمة العزة  "
        },
        {
            "value": 50,
            "isAnswered": false,
            "question": "  كيف يمكن تنمية المثابرة في النفس؟  "
        }
    ],
    "   3": [
        {
            "value": 5,
            "isAnswered": false,
            "question": " من اعطى لقاء حياة متوازنة  "
        },
        {
            "value": 10,
            "isAnswered": false,
            "question": "ما هو مفهوم القيادة "
        },
        {
            "value": 20,
            "isAnswered": false,
            "question": "  اذكر مثالًا تاريخيًا يوضح أهمية المثابرة "
        },
        {
            "value": 40,
            "isAnswered": false,
            "question": "اذكر قول عمر بن الخطاب الذي يعبر عن العزة. "
        },
        {
            "value": 50,
            "isAnswered": false,
            "question": "  استأجر رجل أحد العمال ليخدمه لمدة أسبوع كامل، وكانت الأجرة هي كيلو من الذهب عن كل يوم بشرط أن العامل لا بد أن يأخذ أجرته يومياً، ولدى الرجل سبيكة من الذهب تزن سبعة كيلوجرامات ومعها سكين خاص لتقطيع الذهب مرتين فقط لا غير والسؤال كيف يكون تقطيع الذهب لكي يستطيع العامل أخذ أجرته يومياً ؟ "
        }
    ],
    "  2": [
        {
            "value": 5,
            "isAnswered": false,
            "question": "  هل العدالة تعني المساواة ؟ فسر   "
        },
        {
            "value": 10,
            "isAnswered": false,
            "question": "   اذكر اثنين من الصفات القيادية المهمة. "
        },
        {
            "value": 20,
            "isAnswered": false,
            "question": "كيف يمكن غرس العزة في النفوس؟"
        },
        {
            "value": 40,
            "isAnswered": false,
            "question": "   ما أهمية تحمل المسؤولية في القيادة؟  "
        },
        {
            "value": 50,
            "isAnswered": false,
            "question": "  اذكر حديث النبي ﷺ عن القناعة.     "   
        }
    ],
    " 1": [
        {
            "value": 5,
            "isAnswered": false,
            "question": "   ما الفرق بين العزة والكبر  "
        },
        { "value": 10, "isAnswered": false, "question": " بفيديو مقابلات الملعب ، كم مباراة فاز وخسر ابو لاوي" },
        {
            "value": 20,
            "isAnswered": false,
            "question": "  ما معنى القناعة، ولماذا تُعتبر كنزًا حقيقيًا؟ "
        },
        {
            "value": 40,
            "isAnswered": false,
            "question": " كيف يمكن أن تؤثر العلاقات الاجتماعية في رحلة القائد؟  "
        },
        { "value": 50, "isAnswered": false, "questi on": "   اعطني دليل على ان التوازن منهج رباني" }
    ]
}
